circlus/__init__.py
circlus/models.py
circlus/sampling.py
circlus_py-0.1.0.dist-info/LICENSE
circlus_py-0.1.0.dist-info/METADATA
circlus_py-0.1.0.dist-info/WHEEL
circlus_py-0.1.0.dist-info/top_level.txt
circlus_py-0.1.0.dist-info/RECORD
