Metadata-Version: 2.1
Name: circlus_py
Version: 0.1.0
Summary: Python wrapper for the circlus R package
Author: Lukas Sablica
Requires-Python: >=3.6
License-File: LICENSE
Requires-Dist: rpy2
Requires-Dist: numpy
